pyblish_simple/__init__.py
pyblish_simple/view.py
pyblish_simple-0.0.2.dist-info/METADATA
pyblish_simple-0.0.2.dist-info/WHEEL
pyblish_simple-0.0.2.dist-info/top_level.txt
pyblish_simple-0.0.2.dist-info/RECORD
